MANIFEST.in
README.rst
setup.py
django_intercom_io.egg-info/PKG-INFO
django_intercom_io.egg-info/SOURCES.txt
django_intercom_io.egg-info/dependency_links.txt
django_intercom_io.egg-info/not-zip-safe
django_intercom_io.egg-info/top_level.txt
intercom/__init__.py
intercom/templates/intercom/_intercom_js.html
intercom/templatetags/__init__.py
intercom/templatetags/intercom_tags.py