Metadata-Version: 1.1
Name: django-intercom-io
Version: 0.2.1
Summary: a pluggable app for adding intercom.io to your website
Home-page: https://github.com/eldarion/django-intercom-io
Author: James Tauber
Author-email: developer@eldarion.com
License: BSD
Platform: UNKNOWN
Classifier: Development Status :: 3 - Alpha
Classifier: Environment :: Web Environment
Classifier: Intended Audience :: Developers
Classifier: License :: OSI Approved :: BSD License
Classifier: Operating System :: OS Independent
Classifier: Programming Language :: Python
Classifier: Framework :: Django
